LICENSE
README.md
setup.py
pylocalstorage/__init__.py
pylocalstorage/pylocalstorage.py
pylocalstorage.egg-info/PKG-INFO
pylocalstorage.egg-info/SOURCES.txt
pylocalstorage.egg-info/dependency_links.txt
pylocalstorage.egg-info/top_level.txt
tests/__init__.py
tests/test_pylocalstorage.py