Metadata-Version: 2.1
Name: pylocalstorage
Version: 1.0.3
Summary: A package to store data on the hard disk (HD) and make it available to all Python applications running locally!
Home-page: https://github.com/ferreirad08/pylocalstorage
Author: David Ferreira
Author-email: ferreirad08@gmail.com
License: MIT
Platform: UNKNOWN
Classifier: Programming Language :: Python :: 3
Classifier: License :: OSI Approved :: MIT License
Classifier: Operating System :: OS Independent
Requires-Python: >=2.7
License-File: LICENSE
